spider_XR/__init__.py
spider_XR-0.6.dist-info/METADATA
spider_XR-0.6.dist-info/WHEEL
spider_XR-0.6.dist-info/top_level.txt
spider_XR-0.6.dist-info/RECORD
