Metadata-Version: 2.1
Name: spider_XR
Version: 0.6
Summary: my lib is power
Home-page: https://github.com
Author: spiderXR7
Author-email: spiderxr7@gmail.com
License: MIT
Classifier: Programming Language :: Python :: 3
Classifier: License :: OSI Approved :: MIT License
Requires-Python: >=3.6
